<?xml version="1.0" encoding="utf-8"?>
<!DOCTYPE hibernate-mapping PUBLIC "-//Hibernate/Hibernate Mapping DTD 3.0//EN"
"http://hibernate.sourceforge.net/hibernate-mapping-3.0.dtd">
<!-- 
    Mapping file autogenerated by MyEclipse Persistence Tools
-->
<hibernate-mapping>
    <class name="com.tansun.eam.quequan.model.ETLcYjBO" table="E_T_LC_YJ" >
        <id name="tid" type="java.lang.Long">
            <column name="TID" precision="22" scale="0" />
            <generator class="assigned" />
        </id>
        <property name="yjtjsj" type="java.util.Date">
            <column name="YJTJSJ" length="7" />
        </property>
        <property name="yjtjr" type="java.lang.String">
            <column name="YJTJR" length="40" />
        </property>
        <property name="yjmc" type="java.lang.String">
            <column name="YJMC" length="40" />
        </property>
        <property name="yjnr" type="java.lang.String">
            <column name="YJNR" length="20" />
        </property>
        <property name="cldbh" type="java.lang.Long">
            <column name="CLDBH" precision="22" scale="0" />
        </property>
        <property name="deptId" type="java.lang.Long">
            <column name="DEPT_ID" precision="22" scale="0"  />
        </property>
        <property name="yjlx" type="java.lang.String">
            <column name="YJLX" length="20" />
        </property>
        <property name="hj" type="java.lang.String">
            <column name="HJ" length="2000" />
        </property>
        <property name="flcbh" type="java.lang.Long">
            <column name="FLCBH" precision="22" scale="0" />
        </property>
        <property name="zzyj" type="java.lang.String">
            <column name="ZZYJ" length="20" />
        </property>
        <property name="mkmc" type="java.lang.String">
            <column name="MKMC" length="20" />
        </property>
    </class>
</hibernate-mapping>
