<?xml version="1.0" encoding="utf-8"?>
<!DOCTYPE hibernate-mapping PUBLIC "-//Hibernate/Hibernate Mapping DTD 3.0//EN"
"http://hibernate.sourceforge.net/hibernate-mapping-3.0.dtd">
<!-- 
    Mapping file autogenerated by MyEclipse Persistence Tools
-->
<hibernate-mapping>
    <class name="com.tansun.eam2.common.model.orm.bo.ZyKctz" table="ZY_KCTZ">
        <id name="kctzId" type="java.lang.String">
            <column name="KCTZ_ID" length="32" />
            <generator class="uuid.hex" />
        </id>
        <property name="zcId" type="java.lang.String">
            <column name="ZC_ID" length="32">
                <comment>资产ID</comment>
            </column>
        </property>
        <property name="rq" type="java.util.Date">
            <column name="RQ" length="7">
                <comment>日期</comment>
            </column>
        </property>
        <property name="rksl" type="java.lang.Double">
            <column name="RKSL" precision="20">
                <comment>入库数量</comment>
            </column>
        </property>
        <property name="cksl" type="java.lang.Double">
            <column name="CKSL" precision="20">
                <comment>出库数量</comment>
            </column>
        </property>
        <property name="kcsl" type="java.lang.Double">
            <column name="KCSL" precision="20">
                <comment>库存数量</comment>
            </column>
        </property>
        <property name="lybmbm" type="java.lang.String">
            <column name="LYBMBM" length="20">
                <comment>领用部门编码</comment>
            </column>
        </property>
        <property name="lybmmc" type="java.lang.String">
            <column name="LYBMMC" length="20">
                <comment>领用部门名称</comment>
            </column>
        </property>
        <property name="jybmbm" type="java.lang.String">
            <column name="JYBMBM" length="20">
                <comment>借用部门编码</comment>
            </column>
        </property>
        <property name="jybmmc" type="java.lang.String">
            <column name="JYBMMC" length="20">
                <comment>借用部门名称</comment>
            </column>
        </property>
        <property name="lyrbh" type="java.lang.String">
            <column name="LYRBH" length="20">
                <comment>领用借用人编号</comment>
            </column>
        </property>
        <property name="lyrmc" type="java.lang.String">
            <column name="LYRMC" length="20">
                <comment>领用借用人名称</comment>
            </column>
        </property>
        <property name="lyrq" type="java.util.Date">
            <column name="LYRQ" length="7">
                <comment>领借用日期</comment>
            </column>
        </property>
        <property name="jydqrq" type="java.util.Date">
            <column name="JYDQRQ" length="7">
                <comment>借用到期日期，借用单填写</comment>
            </column>
        </property>
        <property name="bdyy" type="java.lang.String">
            <column name="BDYY" length="20">
                <comment>变动原因</comment>
            </column>
        </property>
        <property name="djlx" type="java.lang.String">
            <column name="DJLX" length="20">
                <comment>对应单据类型：领用单、借用单、续借单、物品更换单、盘盈盘亏单，报废单， 续借两次算领用</comment>
            </column>
        </property>
        <property name="djh" type="java.lang.String">
            <column name="DJH" length="20">
                <comment>对应单据号</comment>
            </column>
        </property>
        <property name="sfzxjl" type="java.lang.Long">
            <column name="SFZXJL" precision="22" scale="0">
                <comment>是否是最新记录，同一资产只有一条最新记录1是0非</comment>
            </column>
        </property>
        <property name="ghsj" type="java.util.Date">
            <column name="GHSJ" length="7">
                <comment>领用借用物品的归还日期</comment>
            </column>
        </property>
        <property name="ghbh" type="java.lang.String">
            <column name="GHBH" length="36">
                <comment>归还申请单编号</comment>
            </column>
        </property>
        <property name="tzzt" type="java.lang.String">
            <column name="TZZT" length="36">
                <comment>台账状态</comment>
            </column>
        </property>
        <property name="bz" type="java.lang.String">
            <column name="BZ" length="1000">
                <comment>备注</comment>
            </column>
        </property>
        <property name="sfxj" type="java.lang.String">
            <column name="SFXJ" length="2">
                <comment>是否续借，只对借用单有效1是0否</comment>
            </column>
        </property>
         <property name="wxfy" type="java.lang.Double">
            <column name="WXFY" length="20">
                <comment>维修费用</comment>
            </column>
        </property>
        <property name="jyts" type="java.lang.Double">
            <column name="JYTS" length="20">
                <comment>借用天数</comment>
            </column>
        </property>
        <property name="ghrbmbm" type="java.lang.String">
            <column name="GHRBMBM" length="100">
                <comment>归还人部门编码</comment>
            </column>
        </property>
        <property name="ghrbmmc" type="java.lang.String">
            <column name="GHRBMMC" length="100">
                <comment>归还人部门名称</comment>
            </column>
        </property>
        <property name="ghrxm" type="java.lang.String">
            <column name="GHRXM" length="100">
                <comment>归还人名称</comment>
            </column>
        </property>
        <property name="ghrbm" type="java.lang.String">
            <column name="GHRBM" length="100">
                <comment>归还人编码</comment>
            </column>
        </property>
    </class>
</hibernate-mapping>
