<?xml version="1.0" encoding="utf-8"?>
<!DOCTYPE hibernate-mapping PUBLIC "-//Hibernate/Hibernate Mapping DTD 3.0//EN"
"http://hibernate.sourceforge.net/hibernate-mapping-3.0.dtd">
<!-- 
    Mapping file autogenerated by MyEclipse Persistence Tools
-->
<hibernate-mapping>
    <class name="com.tansun.eam2.common.model.orm.bo.ZyShead" table="ZY_SHEAD">
        <id name="sheadId" type="java.lang.String">
            <column name="SHEAD_ID" length="32" />
            <generator class="uuid.hex" />
        </id>
        <property name="sheetType" type="java.lang.String">
            <column name="SHEET_TYPE" length="20">
                <comment>表单类型，详见数据字典定义设计</comment>
            </column>
        </property>
        <property name="title" type="java.lang.String">
            <column name="TITLE" length="100">
                <comment>表单标题，手工录入</comment>
            </column>
        </property>
        <property name="sheetId" type="java.lang.String">
            <column name="SHEET_ID" length="100">
                <comment>表单编号，根据编号规则自动生成</comment>
            </column>
        </property>
        <property name="ngrq" type="java.lang.String">
            <column name="NGRQ" length="20">
                <comment>拟稿日期，格式为YYYYMMDD</comment>
            </column>
        </property>
        <property name="ngrbh" type="java.lang.String">
            <column name="NGRBH" length="20">
                <comment>拟稿人编号</comment>
            </column>
        </property>
        <property name="ngrmc" type="java.lang.String">
            <column name="NGRMC" length="20">
                <comment>拟稿人名称</comment>
            </column>
        </property>
        <property name="ngbmbh" type="java.lang.String">
            <column name="NGBMBH" length="20">
                <comment>拟稿部门编号</comment>
            </column>
        </property>
        <property name="ngbmmc" type="java.lang.String">
            <column name="NGBMMC" length="20">
                <comment>拟稿部门名称</comment>
            </column>
        </property>
        <property name="ldxh" type="java.lang.String">
            <column name="LDXH" length="10">
                <comment>联系电话，人工输入</comment>
            </column>
        </property>
        <property name="jhcd" type="java.lang.String">
            <column name="JHCD" length="10">
                <comment>急缓程度1一般；2急；3特急</comment>
            </column>
        </property>
        <property name="ytxq" type="java.lang.String">
            <column name="YTXQ" length="200">
                <comment>用途与需求，采购单专用字段</comment>
            </column>
        </property>
        <property name="cgyj" type="java.lang.String">
            <column name="CGYJ" length="200">
                <comment>采购依据，从其他流程选取单据号或者手工录入</comment>
            </column>
        </property>
        <property name="ngbmyj" type="java.lang.String">
            <column name="NGBMYJ" length="200">
                <comment>拟稿部门意见,此字段废弃</comment>
            </column>
        </property>
        <property name="spbmyj" type="java.lang.String">
            <column name="SPBMYJ" length="200">
                <comment>审批部门意见,此字段废弃</comment>
            </column>
        </property>
        <property name="hqyj" type="java.lang.String">
            <column name="HQYJ" length="200">
                <comment>会签意见,此字段废弃</comment>
            </column>
        </property>
        <property name="ywyyzyj" type="java.lang.String">
            <column name="YWYYZYJ" length="200">
                <comment>业务运营组意见,此字段废弃</comment>
            </column>
        </property>
        <property name="ldpsyj" type="java.lang.String">
            <column name="LDPSYJ" length="200">
                <comment>批示意见此字段废弃</comment>
            </column>
        </property>
        <property name="bdzt" type="java.lang.String">
            <column name="BDZT" length="10">
                <comment>表单状态0 拟稿1进行中2审批完成</comment>
            </column>
        </property>
        <property name="ysrq" type="java.lang.String">
            <column name="YSRQ" length="10">
                <comment>验收日期，格式yyyy-mm-dd</comment>
            </column>
        </property>
        <property name="bfrq" type="java.lang.String">
            <column name="BFRQ" length="10">
                <comment>报废日期YYYY-MM-DD</comment>
            </column>
        </property>
         <property name="hqbm" type="java.lang.String">
            <column name="HQBM" length="10">
                <comment>会签部门</comment>
            </column>
        </property>
         <property name="hqbmId" type="java.lang.String">
            <column name="HQBMID" length="10">
                <comment>会签部门Id</comment>
            </column>
        </property>
         <property name="pdpc" type="java.lang.String">
            <column name="PDPC" length="10">
                <comment>盘点批次</comment>
            </column>
        </property>
    </class>
</hibernate-mapping>
